adaup/__init__.py
adaup/commands/__init__.py
adaup/commands/cardano_cli.py
adaup/commands/cardano_node.py
adaup/commands/hydra.py
adaup/download/__init__.py
adaup/download/etcd.py
adaup/download/exec.py
adaup/download/hydra.py
adaup/download/mithril.py
adaup/download/node.py
adaup/download/node_config.py
adaup-0.1.5.dist-info/METADATA
adaup-0.1.5.dist-info/WHEEL
adaup-0.1.5.dist-info/entry_points.txt
adaup-0.1.5.dist-info/top_level.txt
adaup-0.1.5.dist-info/RECORD
