Metadata-Version: 2.1
Name: adaup
Version: 0.1.5
Summary: A Python package for interacting with Cardano.
Home-page: https://github.com/dquadrant/kuber
Author: Sudip Bhattarai
Author-email: sudip@bhattarai.me
Classifier: Programming Language :: Python :: 3
Classifier: License :: OSI Approved :: MIT License
Classifier: Operating System :: OS Independent
Requires-Python: >=3.6
Requires-Dist: tqdm
